afterflight
