Metadata-Version: 1.0
Name: afterflight
Version: 0.2.1
Summary: An application for analysis of UAV log and video.
Home-page: http://github.com/foobarbecue/afterflight
Author: Aaron Curtis
Author-email: aaron@aarongcurtis.com
License: Apache 2.0, see LICENCE.txt
Platform: UNKNOWN
